README.rst
setup.py
comk_django_plugin/__init__.py
comk_django_plugin/apps.py
comk_django_plugin/update_setting_method.py
comk_django_plugin/urls.py
comk_django_plugin.egg-info/PKG-INFO
comk_django_plugin.egg-info/SOURCES.txt
comk_django_plugin.egg-info/dependency_links.txt
comk_django_plugin.egg-info/requires.txt
comk_django_plugin.egg-info/top_level.txt
comk_django_plugin/loghandler/__init__.py
comk_django_plugin/loghandler/multiprocessloghandler.py
comk_django_plugin/logsetting/__init__.py
comk_django_plugin/logsetting/comk_setting.py
comk_django_plugin/logsetting/default_logsetting.py
comk_django_plugin/middleware/ErrorLogMiddleware.py
comk_django_plugin/middleware/RequestLogMiddleware.py
comk_django_plugin/middleware/__init__.py
comk_django_plugin/utils/BaseMoudel.py
comk_django_plugin/utils/GeneralMethods.py
comk_django_plugin/utils/PublicDao.py
comk_django_plugin/utils/PublicServer.py
comk_django_plugin/utils/__init__.py
comk_django_plugin/views/LogView.py
comk_django_plugin/views/__init__.py