Metadata-Version: 1.2
Name: comk-django-plugin
Version: 1.4.4
Summary: comk个人开发的django插件，用于很方便的记录日志、下载日志，以及其他拥有小功能的中间件
Home-page: UNKNOWN
Author: comk
Author-email: 1943336161@qq.com
Maintainer: comk
Maintainer-email: 1943336161@qq.com
License: BSD License
Platform: all
Classifier: Development Status :: 4 - Beta
Classifier: Operating System :: OS Independent
Classifier: Intended Audience :: Developers
Classifier: License :: OSI Approved :: BSD License
Classifier: Programming Language :: Python
Classifier: Programming Language :: Python :: Implementation
Classifier: Programming Language :: Python :: 3
Classifier: Programming Language :: Python :: 3.4
Classifier: Programming Language :: Python :: 3.5
Classifier: Programming Language :: Python :: 3.6
Classifier: Topic :: Software Development :: Libraries
